tonga/__init__.py
tonga/errors.py
tonga/models/__init__.py
tonga/models/events/__init__.py
tonga/models/events/base.py
tonga/models/events/command/__init__.py
tonga/models/events/command/command.py
tonga/models/events/command/errors.py
tonga/models/events/event/__init__.py
tonga/models/events/event/event.py
tonga/models/events/result/__init__.py
tonga/models/events/result/result.py
tonga/models/handlers/base.py
tonga/models/handlers/command/__init__.py
tonga/models/handlers/command/command_handler.py
tonga/models/handlers/event/__init__.py
tonga/models/handlers/event/event_handler.py
tonga/models/handlers/result/__init__.py
tonga/models/handlers/result/result_handler.py
tonga/models/store_record/__init__.py
tonga/models/store_record/base.py
tonga/models/store_record/errors.py
tonga/models/store_record/store_record.py
tonga/models/store_record/store_record_handler.py
tonga/models/store_record/avro_schema/store_record.avsc.yaml
tonga/services/__init__.py
tonga/services/errors.py
tonga/services/consumer/__init__.py
tonga/services/consumer/base.py
tonga/services/consumer/errors.py
tonga/services/consumer/kafka_consumer.py
tonga/services/coordinator/__init__.py
tonga/services/coordinator/assignors/__init__.py
tonga/services/coordinator/assignors/errors.py
tonga/services/coordinator/assignors/statefulset_assignors.py
tonga/services/coordinator/partitioner/__init__.py
tonga/services/coordinator/partitioner/base.py
tonga/services/coordinator/partitioner/errors.py
tonga/services/coordinator/partitioner/key_partitioner.py
tonga/services/coordinator/partitioner/statefulset_partitioner.py
tonga/services/producer/__init__.py
tonga/services/producer/base.py
tonga/services/producer/errors.py
tonga/services/producer/kafka_producer.py
tonga/services/serializer/__init__.py
tonga/services/serializer/avro.py
tonga/services/serializer/base.py
tonga/services/serializer/errors.py
tonga/services/serializer/kafka_key.py
tonga/stores/__init__.py
tonga/stores/base.py
tonga/stores/errors.py
tonga-0.0.2.dist-info/AUTHORS
tonga-0.0.2.dist-info/LICENSE
tonga-0.0.2.dist-info/METADATA
tonga-0.0.2.dist-info/WHEEL
tonga-0.0.2.dist-info/top_level.txt
tonga-0.0.2.dist-info/RECORD
